dimod/__init__.pxd
dimod/__init__.py
dimod/binary_quadratic_model.py
dimod/converters.py
dimod/cylp.cpp
dimod/cylp.cpython-314-aarch64-linux-gnu.so
dimod/cylp.pxd
dimod/cylp.pyx
dimod/cyutilities.cpp
dimod/cyutilities.cpython-314-aarch64-linux-gnu.so
dimod/cyutilities.pxd
dimod/cyutilities.pyx
dimod/cyvariables.cpp
dimod/cyvariables.cpython-314-aarch64-linux-gnu.so
dimod/cyvariables.pxd
dimod/cyvariables.pyi
dimod/cyvariables.pyx
dimod/decorators.py
dimod/exceptions.py
dimod/lp.py
dimod/package_info.py
dimod/py.typed
dimod/sampleset.py
dimod/sym.py
dimod/traversal.py
dimod/typing.pxd
dimod/typing.py
dimod/utilities.py
dimod/variables.py
dimod/vartypes.py
dimod/binary/__init__.pxd
dimod/binary/__init__.py
dimod/binary/binary_quadratic_model.py
dimod/binary/pybqm.py
dimod/binary/vartypeview.py
dimod/binary/cybqm/__init__.pxd
dimod/binary/cybqm/__init__.py
dimod/binary/cybqm/cybqm_float32.cpp
dimod/binary/cybqm/cybqm_float32.cpython-314-aarch64-linux-gnu.so
dimod/binary/cybqm/cybqm_float32.pxd
dimod/binary/cybqm/cybqm_float32.pyx
dimod/binary/cybqm/cybqm_float64.cpp
dimod/binary/cybqm/cybqm_float64.cpython-314-aarch64-linux-gnu.so
dimod/binary/cybqm/cybqm_float64.pxd
dimod/binary/cybqm/cybqm_float64.pyx
dimod/binary/cybqm/cybqm_template.pxd.pxi
dimod/binary/cybqm/cybqm_template.pyx.pxi
dimod/constrained/__init__.pxd
dimod/constrained/__init__.py
dimod/constrained/constrained.py
dimod/constrained/cyconstrained.cpp
dimod/constrained/cyconstrained.cpython-314-aarch64-linux-gnu.so
dimod/constrained/cyconstrained.pxd
dimod/constrained/cyconstrained.pyx
dimod/constrained/cyexpression.cpp
dimod/constrained/cyexpression.cpython-314-aarch64-linux-gnu.so
dimod/constrained/cyexpression.pxd
dimod/constrained/cyexpression.pyx
dimod/constrained/expression.py
dimod/core/__init__.py
dimod/core/composite.py
dimod/core/initialized.py
dimod/core/polysampler.py
dimod/core/sampler.py
dimod/core/scoped.py
dimod-0.12.21.dist-info/METADATA
dimod-0.12.21.dist-info/WHEEL
dimod-0.12.21.dist-info/top_level.txt
dimod-0.12.21.dist-info/RECORD
dimod-0.12.21.dist-info/licenses/LICENSE
