Metadata-Version: 2.4
Name: dimod
Version: 0.12.21
Summary: A shared API for binary quadratic model samplers.
Home-page: https://github.com/dwavesystems/dimod
Download-URL: https://github.com/dwavesystems/dimod/releases
Author: D-Wave Systems Inc.
Author-email: tools@dwavesys.com
License: Apache 2.0
Classifier: License :: OSI Approved :: Apache Software License
Classifier: Operating System :: Microsoft :: Windows
Classifier: Operating System :: POSIX
Classifier: Operating System :: Unix
Classifier: Operating System :: MacOS
Classifier: Programming Language :: C++
Classifier: Programming Language :: Cython
Classifier: Programming Language :: Python
Classifier: Programming Language :: Python :: 3
Classifier: Programming Language :: Python :: 3.9
Classifier: Programming Language :: Python :: 3.10
Classifier: Programming Language :: Python :: 3.11
Classifier: Programming Language :: Python :: 3.12
Classifier: Programming Language :: Python :: 3.13
Classifier: Programming Language :: Python :: 3 :: Only
Classifier: Programming Language :: Python :: Implementation :: CPython
Requires-Python: >=3.9
License-File: LICENSE
Requires-Dist: numpy>=1.17.3
Provides-Extra: all
Dynamic: download-url
Dynamic: license-file
Dynamic: provides-extra
Dynamic: requires-dist
